CHANGES.txt
MANIFEST.in
README.txt
setup.cfg
setup.py
src/slapos/__init__.py
src/slapos.recipe.sheepdogtestbed.egg-info/PKG-INFO
src/slapos.recipe.sheepdogtestbed.egg-info/SOURCES.txt
src/slapos.recipe.sheepdogtestbed.egg-info/dependency_links.txt
src/slapos.recipe.sheepdogtestbed.egg-info/entry_points.txt
src/slapos.recipe.sheepdogtestbed.egg-info/namespace_packages.txt
src/slapos.recipe.sheepdogtestbed.egg-info/requires.txt
src/slapos.recipe.sheepdogtestbed.egg-info/top_level.txt
src/slapos/recipe/__init__.py
src/slapos/recipe/sheepdogtestbed/__init__.py
src/slapos/recipe/sheepdogtestbed/template/nosqltester_manager_run.in
src/slapos/recipe/sheepdogtestbed/template/nosqltester_run.in