Metadata-Version: 1.0
Name: slapos.recipe.sheepdogtestbed
Version: 0.0.1.dev
Summary: ZC Buildout recipe for the sheepdog test bed
Home-page: UNKNOWN
Author: UNKNOWN
Author-email: UNKNOWN
License: GPLv3
Keywords: buildout sheepdogtestbed
Platform: UNKNOWN
Classifier: Framework :: Buildout :: Recipe
Classifier: Programming Language :: Python
